typstwriter/__init__.py
typstwriter/actions.py
typstwriter/arguments.py
typstwriter/compiler.py
typstwriter/compiler_tools.py
typstwriter/configuration.py
typstwriter/editor.py
typstwriter/enums.py
typstwriter/fs_explorer.py
typstwriter/globalstate.py
typstwriter/logging.py
typstwriter/mainwindow.py
typstwriter/menubar.py
typstwriter/pdf_viewer.py
typstwriter/syntax_highlighting.py
typstwriter/toolbar.py
typstwriter/typstwriter.py
typstwriter/util.py
typstwriter/icons/close.svg
typstwriter/icons/closeFile.svg
typstwriter/icons/copy.svg
typstwriter/icons/cut.svg
typstwriter/icons/darrow.svg
typstwriter/icons/deleteFile.svg
typstwriter/icons/folder.svg
typstwriter/icons/ignore.svg
typstwriter/icons/larrow.svg
typstwriter/icons/lastSession.svg
typstwriter/icons/minus.svg
typstwriter/icons/newFile.svg
typstwriter/icons/openFile.svg
typstwriter/icons/parent_dir.svg
typstwriter/icons/paste.svg
typstwriter/icons/pdf.svg
typstwriter/icons/plus.svg
typstwriter/icons/quit.svg
typstwriter/icons/rarrow.svg
typstwriter/icons/recentFile.svg
typstwriter/icons/reload.svg
typstwriter/icons/save.svg
typstwriter/icons/save_as.svg
typstwriter/icons/search.svg
typstwriter/icons/start.svg
typstwriter/icons/stop.svg
typstwriter/icons/typst.png
typstwriter/icons/typstwriter.svg
typstwriter/icons/uarrow.svg
typstwriter/icons/warning.svg
typstwriter-0.3.dist-info/entry_points.txt
typstwriter-0.3.dist-info/LICENSE
typstwriter-0.3.dist-info/WHEEL
typstwriter-0.3.dist-info/METADATA
typstwriter-0.3.dist-info/RECORD
