Metadata-Version: 2.3
Name: typstwriter
Version: 0.3
Summary: An integrated editor for the typst typesetting system.
Keywords: typst
Author-email: Bzero <B_0@posteo.net>
Requires-Python: >=3.10
Classifier: Programming Language :: Python :: 3
Classifier: License :: OSI Approved :: MIT License
Classifier: Operating System :: POSIX :: Linux
Classifier: Operating System :: Microsoft :: Windows
Classifier: Environment :: X11 Applications :: Qt
Classifier: Intended Audience :: End Users/Desktop
Classifier: Topic :: Text Editors
Classifier: Topic :: Text Editors :: Word Processors
Requires-Dist: qtpy >= 2.3
Requires-Dist: pyside6 >= 6.4.0
Requires-Dist: pygments >= 2.18
Requires-Dist: platformdirs >= 4.0
Requires-Dist: pytest ; extra == "tests"
Requires-Dist: pytest-qt ; extra == "tests"
Requires-Dist: fpdf ; extra == "tests"
Project-URL: Repository, https://github.com/Bzero/typstwriter
Provides-Extra: tests
